st_yled/__init__.py
st_yled/colors.py
st_yled/components/badge_card_one/__init__.py
st_yled/components/base.py
st_yled/components/image_card_one/__init__.py
st_yled/components/sticky_header/__init__.py
st_yled/components/streamlit_redirect/__init__.py
st_yled/components/streamlit_split_button/__init__.py
st_yled/components.json
st_yled/constants.py
st_yled/css_color_names.json
st_yled/element_styles.json
st_yled/elements.py
st_yled/styler.py
st_yled/validation.py
st_styled-0.3.0.dist-info/METADATA
st_styled-0.3.0.dist-info/WHEEL
st_styled-0.3.0.dist-info/RECORD
