Metadata-Version: 2.4
Name: st-styled
Version: 0.3.0
Summary: Advanced styling and custom components for Streamlit applications
License: MIT
Keywords: streamlit,styling,css,components,ui
Author: JonathanAlles
Author-email: Jonathan.Alles@evo-byte.com
Requires-Python: >=3.10
Classifier: Development Status :: 3 - Alpha
Classifier: Intended Audience :: Developers
Classifier: License :: OSI Approved :: MIT License
Classifier: Programming Language :: Python :: 3
Classifier: Programming Language :: Python :: 3.10
Classifier: Programming Language :: Python :: 3.11
Classifier: Programming Language :: Python :: 3.12
Classifier: Programming Language :: Python :: 3.13
Classifier: Programming Language :: Python :: 3.14
Classifier: Topic :: Software Development :: Libraries :: Python Modules
Classifier: Topic :: Software Development :: User Interfaces
Provides-Extra: dev
Requires-Dist: mypy (>=1.5.0) ; extra == "dev"
Requires-Dist: openpyxl (>=3.1.5,<4.0.0)
Requires-Dist: pandas (>=2.0.0,<3.0.0)
Requires-Dist: pre-commit (>=3.0.0) ; extra == "dev"
Requires-Dist: pytest (>=7.0.0) ; extra == "dev"
Requires-Dist: pytest-cov (>=4.0.0) ; extra == "dev"
Requires-Dist: ruff (>=0.1.0) ; extra == "dev"
Requires-Dist: streamlit (>=1.47.0)
Project-URL: Documentation, https://st-styled.evo-byte.com/
Project-URL: Homepage, https://st-styled.evo-byte.com/
Project-URL: Issues, https://github.com/EvobyteDigitalBiology/st-styled/issues
Project-URL: Repository, https://github.com/EvobyteDigitalBiology/st-styled
